{
    "Ar36": {
        "error": 0.0003684903645306047,
        "error_type": "SEM",
        "filter_outliers_dict": {
            "filter_outliers": true,
            "iterations": 1,
            "std_devs": 2,
            "use_iqr_filtering": false,
            "use_standard_deviation_filtering": false
        },
        "fit": "Linear",
        "fn": 114,
        "include_baseline_error": false,
        "n": 120,
        "outlier_excluded": [
            46,
            112,
            18,
            50,
            22,
            58
        ],
        "reviewed": true,
        "user_excluded": [],
        "value": 0.021842625641483267
    },
    "Ar37": {
        "error": 0.009750978362765273,
        "error_type": "SEM",
        "filter_outliers_dict": {
            "filter_outliers": true,
            "iterations": 1,
            "std_devs": 2,
            "use_iqr_filtering": false,
            "use_standard_deviation_filtering": false
        },
        "fit": "Linear",
        "fn": 116,
        "include_baseline_error": false,
        "n": 120,
        "outlier_excluded": [
            25,
            41,
            68,
            39
        ],
        "reviewed": true,
        "user_excluded": [],
        "value": 1.0563881648571933
    },
    "Ar38": {
        "error": 0.005887705360879727,
        "error_type": "SEM",
        "filter_outliers_dict": {
            "filter_outliers": true,
            "iterations": 1,
            "std_devs": 2,
            "use_iqr_filtering": false,
            "use_standard_deviation_filtering": false
        },
        "fit": "Linear",
        "fn": 115,
        "include_baseline_error": false,
        "n": 120,
        "outlier_excluded": [
            34,
            66,
            36,
            76,
            22
        ],
        "reviewed": true,
        "user_excluded": [],
        "value": 3.498722508823203
    },
    "Ar39": {
        "error": 0.027753634751121505,
        "error_type": "SEM",
        "filter_outliers_dict": {
            "filter_outliers": true,
            "iterations": 1,
            "std_devs": 2,
            "use_iqr_filtering": false,
            "use_standard_deviation_filtering": false
        },
        "fit": "Linear",
        "fn": 115,
        "include_baseline_error": false,
        "n": 120,
        "outlier_excluded": [
            4,
            109,
            78,
            92,
            93
        ],
        "reviewed": true,
        "user_excluded": [],
        "value": 281.7904524073003
    },
    "Ar40": {
        "error": 0.0851956218382853,
        "error_type": "SEM",
        "filter_outliers_dict": {
            "filter_outliers": true,
            "iterations": 1,
            "std_devs": 2,
            "use_iqr_filtering": false,
            "use_standard_deviation_filtering": false
        },
        "fit": "Linear",
        "fn": 112,
        "include_baseline_error": false,
        "n": 120,
        "outlier_excluded": [
            1,
            2,
            3,
            72,
            73,
            108,
            17,
            55
        ],
        "reviewed": true,
        "user_excluded": [],
        "value": 2322.7688541975836
    },
    "Ar41": {
        "error": 0.0017605811559716351,
        "error_type": "SEM",
        "filter_outliers_dict": {
            "filter_outliers": true,
            "iterations": 1,
            "std_devs": 2
        },
        "fit": "Average",
        "value": 0.05315456098422567
    }
}